langgraph_runtime_firestore/README.md
langgraph_runtime_firestore/__init__.py
langgraph_runtime_firestore/checkpoint.py
langgraph_runtime_firestore/database.py
langgraph_runtime_firestore/firestore_stream.py
langgraph_runtime_firestore/lifespan.py
langgraph_runtime_firestore/metrics.py
langgraph_runtime_firestore/ops.py
langgraph_runtime_firestore/queue.py
langgraph_runtime_firestore/retry.py
langgraph_runtime_firestore/serialize.py
langgraph_runtime_firestore/store.py
langgraph_runtime_firestore/utils.py
langgraph_runtime_firestore-1.0.4.dist-info/METADATA
langgraph_runtime_firestore-1.0.4.dist-info/WHEEL
langgraph_runtime_firestore-1.0.4.dist-info/licenses/LICENSE
langgraph_runtime_firestore-1.0.4.dist-info/RECORD
