Metadata-Version: 2.4
Name: langgraph-runtime-firestore
Version: 1.0.4
Summary: Firestore runtime implementation for LangGraph.
Project-URL: Homepage, https://github.com/MarcoFurrer/langgraph_runtime_firestore
Project-URL: Repository, https://github.com/MarcoFurrer/langgraph_runtime_firestore
Project-URL: Issues, https://github.com/MarcoFurrer/langgraph_runtime_firestore/issues
Author: Marco Furrer
License: Elastic-2.0
License-File: LICENSE
Keywords: ai,firestore,graph,langchain,langgraph,workflow
Classifier: Development Status :: 4 - Beta
Classifier: Intended Audience :: Developers
Classifier: License :: Other/Proprietary License
Classifier: Programming Language :: Python :: 3
Classifier: Programming Language :: Python :: 3.11
Classifier: Programming Language :: Python :: 3.12
Classifier: Topic :: Scientific/Engineering :: Artificial Intelligence
Classifier: Topic :: Software Development :: Libraries :: Python Modules
Requires-Python: >=3.11.0
Requires-Dist: blockbuster<2.0.0,>=1.5.24
Requires-Dist: firebase-admin>=6.0.0
Requires-Dist: langgraph-checkpoint<4,>=3
Requires-Dist: langgraph<2,>=0.4.10
Requires-Dist: sse-starlette>=2
Requires-Dist: starlette>=0.37
Requires-Dist: structlog>23
